asyncio_helper
