Metadata-Version: 1.1
Name: asyncio-helper
Version: 0.1.3
Summary: Library of helper functions for asyncio
Home-page: https://github.com/strangedev/asyncio-helper
Author: strangedev
Author-email: strangedev@posteo.net
License: Apache 2.0
Download-URL: https://github.com/strangedev/asyncio-helper/tarball/v0.1.3
Keywords: asyncio helper
Platform: UNKNOWN
Classifier: Development Status :: 3 - Alpha
Classifier: Operating System :: POSIX
Classifier: Operating System :: MacOS
Classifier: Operating System :: Unix
Classifier: Intended Audience :: Developers
Classifier: Topic :: Software Development :: Libraries
Classifier: Programming Language :: Python :: 3.7
Classifier: Programming Language :: Python :: 3 :: Only
